errbot/__init__.py
errbot/backend_plugin_manager.py
errbot/bootstrap.py
errbot/botplugin.py
errbot/cli.py
errbot/config-template.py
errbot/core.py
errbot/flow.py
errbot/logs.py
errbot/plugin_info.py
errbot/plugin_manager.py
errbot/plugin_wizard.py
errbot/repo_manager.py
errbot/streaming.py
errbot/templating.py
errbot/utils.py
errbot/version.py
errbot/backends/__init__.py
errbot/backends/base.py
errbot/backends/irc.plug
errbot/backends/irc.py
errbot/backends/null.plug
errbot/backends/null.py
errbot/backends/telegram_messenger.plug
errbot/backends/telegram_messenger.py
errbot/backends/test.plug
errbot/backends/test.py
errbot/backends/text.plug
errbot/backends/text.py
errbot/backends/xmpp.plug
errbot/backends/xmpp.py
errbot/backends/images/errbot-bg.svg
errbot/backends/images/errbot.svg
errbot/backends/images/prompt.svg
errbot/backends/styles/style-demo.css
errbot/backends/styles/style.css
errbot/core_plugins/__init__.py
errbot/core_plugins/acls.plug
errbot/core_plugins/acls.py
errbot/core_plugins/backup.plug
errbot/core_plugins/backup.py
errbot/core_plugins/chatRoom.plug
errbot/core_plugins/chatRoom.py
errbot/core_plugins/cnf_filter.plug
errbot/core_plugins/cnf_filter.py
errbot/core_plugins/flows.plug
errbot/core_plugins/flows.py
errbot/core_plugins/health.plug
errbot/core_plugins/health.py
errbot/core_plugins/help.plug
errbot/core_plugins/help.py
errbot/core_plugins/plugins.plug
errbot/core_plugins/plugins.py
errbot/core_plugins/test.md
errbot/core_plugins/textcmds.plug
errbot/core_plugins/textcmds.py
errbot/core_plugins/utils.plug
errbot/core_plugins/utils.py
errbot/core_plugins/vcheck.plug
errbot/core_plugins/vcheck.py
errbot/core_plugins/webserver.plug
errbot/core_plugins/webserver.py
errbot/core_plugins/wsview.py
errbot/core_plugins/templates/about.md
errbot/core_plugins/templates/plugin_info.md
errbot/core_plugins/templates/repos.md
errbot/core_plugins/templates/repos2.md
errbot/core_plugins/templates/status.md
errbot/core_plugins/templates/status_gc.md
errbot-6.2.0.dist-info/COPYING
errbot-6.2.0.dist-info/METADATA
errbot-6.2.0.dist-info/WHEEL
errbot-6.2.0.dist-info/entry_points.txt
errbot-6.2.0.dist-info/top_level.txt
errbot-6.2.0.dist-info/RECORD
