Metadata-Version: 2.1
Name: errbot
Version: 6.2.0
Summary: Errbot is a chatbot designed to be simple to extend with plugins written in Python.
Home-page: http://errbot.io/
Author: errbot.io
Author-email: info@errbot.io
License: GPL
Keywords: xmpp irc slack hipchat gitter tox chatbot bot plugin chatops
Platform: any
Classifier: Development Status :: 5 - Production/Stable
Classifier: Topic :: Communications :: Chat
Classifier: Topic :: Communications :: Chat :: Internet Relay Chat
Classifier: License :: OSI Approved :: GNU General Public License v3 (GPLv3)
Classifier: Operating System :: OS Independent
Classifier: Programming Language :: Python :: 3
Classifier: Programming Language :: Python :: 3.8
Classifier: Programming Language :: Python :: 3.9
Classifier: Programming Language :: Python :: 3.10
License-File: COPYING
Requires-Dist: webtest ==3.0.0
Requires-Dist: setuptools ==68.1.2
Requires-Dist: flask ==2.3.3
Requires-Dist: requests ==2.31.0
Requires-Dist: jinja2 ==3.1.2
Requires-Dist: pyOpenSSL ==23.2.0
Requires-Dist: colorlog ==6.7.0
Requires-Dist: markdown ==3.4.4
Requires-Dist: ansi ==0.3.6
Requires-Dist: Pygments ==2.16.1
Requires-Dist: pygments-markdown-lexer ==0.1.0.dev39
Requires-Dist: dulwich ==0.21.5
Requires-Dist: deepmerge ==1.1.0
Requires-Dist: daemonize ==2.5.0 ; sys_platform!="win32"
Provides-Extra: irc
Requires-Dist: irc ==20.3.0 ; extra == 'irc'
Provides-Extra: xmpp
Requires-Dist: slixmpp ==1.8.4 ; extra == 'xmpp'
Requires-Dist: pyasn1 ==0.5.0 ; extra == 'xmpp'
Requires-Dist: pyasn1-modules ==0.3.0 ; extra == 'xmpp'
Provides-Extra: discord
Requires-Dist: err-backend-discord ==3.0.1 ; extra == 'discord'
Provides-Extra: mattermost
Requires-Dist: err-backend-mattermost ==3.0.0 ; extra == 'mattermost'
Provides-Extra: slack
Requires-Dist: errbot-backend-slackv3 ==0.2.1 ; extra == 'slack'
Provides-Extra: telegram
Requires-Dist: python-telegram-bot ==13.15 ; extra == 'telegram'
